{"errors":[],"warnings":[],"namedChunkGroups":{"app":{"chunks":[5,0,2],"assets":["webpack-runtime-5443f96108a34bdcfdfe.js","webpack-runtime-5443f96108a34bdcfdfe.js.map","commons-902bd1f3add3f8c2fb43.js","commons-902bd1f3add3f8c2fb43.js.map","app-2a10b3d3aaae4582922f.js","app-2a10b3d3aaae4582922f.js.map"],"children":{},"childAssets":{}},"component---src-pages-404-js":{"chunks":[1,0,3],"assets":["styles.d91b2dabb4556f26bc20.css","styles-b70a00b310262b7fe12e.js","styles-b70a00b310262b7fe12e.js.map","commons-902bd1f3add3f8c2fb43.js","commons-902bd1f3add3f8c2fb43.js.map","component---src-pages-404-js-844570e8e3e4f500f609.js","component---src-pages-404-js-844570e8e3e4f500f609.js.map"],"children":{},"childAssets":{}},"component---src-pages-index-js":{"chunks":[1,0,4],"assets":["styles.d91b2dabb4556f26bc20.css","styles-b70a00b310262b7fe12e.js","styles-b70a00b310262b7fe12e.js.map","commons-902bd1f3add3f8c2fb43.js","commons-902bd1f3add3f8c2fb43.js.map","component---src-pages-index-js-bca7816578d9e62fc50d.js","component---src-pages-index-js-bca7816578d9e62fc50d.js.map"],"children":{},"childAssets":{}}},"assetsByChunkName":{"app":["webpack-runtime-5443f96108a34bdcfdfe.js","commons-902bd1f3add3f8c2fb43.js","app-2a10b3d3aaae4582922f.js"],"component---src-pages-404-js":["styles.d91b2dabb4556f26bc20.css","styles-b70a00b310262b7fe12e.js","commons-902bd1f3add3f8c2fb43.js","component---src-pages-404-js-844570e8e3e4f500f609.js"],"component---src-pages-index-js":["styles.d91b2dabb4556f26bc20.css","styles-b70a00b310262b7fe12e.js","commons-902bd1f3add3f8c2fb43.js","component---src-pages-index-js-bca7816578d9e62fc50d.js"]}}